testexecutor/VERSION
testexecutor/__init__.py
testexecutor/control/TestListenerApi.py
testexecutor/control/TestSuiteListener.py
testexecutor/control/__init__.py
testexecutor/model/GenericListModel.py
testexecutor/model/InstructionsModel.py
testexecutor/model/KeyValueModel.py
testexecutor/model/MultiTestWindowModel.py
testexecutor/model/ResultModel.py
testexecutor/model/TestSuiteControlModel.py
testexecutor/model/TestSuiteGroup.py
testexecutor/model/TestSuiteModel.py
testexecutor/model/__init__.py
testexecutor/model/selector/FilterGroupModel.py
testexecutor/model/selector/FilterModel.py
testexecutor/model/selector/MultiSelectDetails.py
testexecutor/model/selector/MultiSelectListModel.py
testexecutor/model/selector/__init__.py
testexecutor/ui/IdentificationWidget.qml
testexecutor/ui/InputWidget.qml
testexecutor/ui/InstructionWidget.qml
testexecutor/ui/KeyValueItem.qml
testexecutor/ui/KeyValueItemConfig.qml
testexecutor/ui/KeyValueList.qml
testexecutor/ui/MultiTestWidget.qml
testexecutor/ui/MultiTestWindow.qml
testexecutor/ui/ResultItem.qml
testexecutor/ui/ResultItemConfig.qml
testexecutor/ui/ResultList.qml
testexecutor/ui/TestSuiteConfig.qml
testexecutor/ui/TestSuiteController.qml
testexecutor/ui/TestSuiteWidget.qml
testexecutor/ui/te-64x64.ico
testexecutor/ui/selector/FilterItem.qml
testexecutor/ui/selector/FilterItemConfig.qml
testexecutor/ui/selector/FilterMultiSelectorItem.qml
testexecutor/ui/selector/FilterMultiSelectorItemConfig.qml
testexecutor/ui/selector/FilterMultiSelectorList.qml
testexecutor/ui/selector/HeaderConfig.qml
testexecutor/ui/selector/SectionConfig.qml
testexecutor/ui/selector/SectionDelegate.qml
testexecutor/ui/selector/SelectorHeader.qml
testexecutor/ui/selector/SuiteList.qml
testexecutor/ui/selector/SuiteSelector.qml
testexecutor/ui/selector/SuiteSelectorConfig.qml
testexecutor/ui/selector/TestConfig.qml
testexecutor/ui/selector/TestDelegate.qml
testexecutor_ui-0.6.1.dist-info/LICENSE
testexecutor_ui-0.6.1.dist-info/METADATA
testexecutor_ui-0.6.1.dist-info/NOTICE
testexecutor_ui-0.6.1.dist-info/WHEEL
testexecutor_ui-0.6.1.dist-info/top_level.txt
testexecutor_ui-0.6.1.dist-info/RECORD
