Metadata-Version: 2.1
Name: testexecutor-ui
Version: 0.6.1
Summary: A python UI library for the execution and control of device tests
Home-page: https://www.direktembedded.com
Classifier: Programming Language :: Python :: 3
Classifier: License :: OSI Approved :: Apache Software License
Classifier: Operating System :: OS Independent
Requires-Python: >=3.6
License-File: LICENSE
License-File: NOTICE
Requires-Dist: PySide6 >=6.2
